pearson/__init__.py
pearson/brain.json
pearson/data.pth
pearson/main.py
pearson/model.py
pearson/pearson.py
pearson/train.py
pearson/__pycache__/__init__.cpython-311.pyc
pearson/__pycache__/main.cpython-311.pyc
pearson/__pycache__/model.cpython-311.pyc
pearson/__pycache__/pearson.cpython-311.pyc
pearson-2.9.dist-info/METADATA
pearson-2.9.dist-info/WHEEL
pearson-2.9.dist-info/top_level.txt
pearson-2.9.dist-info/RECORD
