Metadata-Version: 2.1
Name: pearson
Version: 2.9
Summary: A simple chatbot that can be trained to answer questions based on a dataset
Home-page: https://github.com/mjfactor/Mr-Pearson
Author: mjfactor
Author-email: emjayfactor@gmail.com
Classifier: Development Status :: 3 - Alpha
Classifier: Intended Audience :: Developers
Classifier: License :: OSI Approved :: MIT License
Classifier: Programming Language :: Python :: 3.7
Classifier: Programming Language :: Python :: 3.9
Classifier: Programming Language :: Python :: 3.8
Classifier: Programming Language :: Python :: 3.11
Classifier: Programming Language :: Python :: 3.10
Classifier: Operating System :: OS Independent
Requires-Python: >=3.7
Requires-Dist: nltk
Requires-Dist: torch
